dbcalc.py
dbcalc-0.1.4.dist-info/DESCRIPTION.rst
dbcalc-0.1.4.dist-info/METADATA
dbcalc-0.1.4.dist-info/RECORD
dbcalc-0.1.4.dist-info/WHEEL
dbcalc-0.1.4.dist-info/entry_points.txt
dbcalc-0.1.4.dist-info/metadata.json
dbcalc-0.1.4.dist-info/top_level.txt
