Metadata-Version: 2.0
Name: dbcalc
Version: 0.1.4
Summary: A dB <-> power calculator for the command line
Home-page: https://bitbucket.org/Vieler/dbcalc/
Author: Vieler Hyloks
Author-email: vielerhyloks@gmail.com
License: UNKNOWN
Platform: UNKNOWN
Classifier: Development Status :: 4 - Beta
Classifier: Environment :: Console
Classifier: License :: OSI Approved :: GNU General Public License v3 or later (GPLv3+)
Classifier: Operating System :: OS Independent
Classifier: Programming Language :: Python
Classifier: Topic :: Scientific/Engineering :: Physics
